README.md
setup.py
scene_manager/__init__.py
scene_manager/exceptions.py
scene_manager/middleware.py
scene_manager/utils.py
scene_manager.egg-info/PKG-INFO
scene_manager.egg-info/SOURCES.txt
scene_manager.egg-info/dependency_links.txt
scene_manager.egg-info/requires.txt
scene_manager.egg-info/top_level.txt
scene_manager/loader/__init__.py
scene_manager/loader/loader.py
scene_manager/loader/models.py
scene_manager/loader/utils.py
scene_manager/scenes/__init__.py
scene_manager/scenes/base.py
scene_manager/scenes/samples.py
scene_manager/settings/__init__.py
scene_manager/settings/storage.py
scene_manager/storages/__init__.py
scene_manager/storages/base.py
scene_manager/storages/redis.py
scene_manager/storages/types.py
scene_manager/tools/__init__.py
scene_manager/tools/filters.py