Metadata-Version: 1.2
Name: scene-manager
Version: 0.1.0
Summary: Scenes manager for aiogram
Home-page: https://github.com/Bloodielie/scene_manager
Author: Bloodie_lie
Author-email: riopro2812@gmail.com
License: MIT
Platform: UNKNOWN
Requires-Python: >=3.7
